pixelmemory/__init__.py
pixelmemory/memory.py
pixelmemory-0.1.0.dist-info/LICENSE
pixelmemory-0.1.0.dist-info/METADATA
pixelmemory-0.1.0.dist-info/WHEEL
pixelmemory-0.1.0.dist-info/RECORD
