Metadata-Version: 2.3
Name: pixelmemory
Version: 0.1.0
Summary: Multimodal Memory for AI Agents and MCP.
License: Apache-2.0
Keywords: data-science,machine-learning,database,ai,computer-vision,chatbot,ml,artificial-intelligence,feature-engineering,multimodal,mlops,feature-store,vector-database,llm,genai
Author: Pixeltable, Inc.
Author-email: contact@pixeltable.com>
Requires-Python: >=3.9,<4.0
Classifier: Intended Audience :: Developers
Classifier: Intended Audience :: Science/Research
Classifier: License :: OSI Approved :: Apache Software License
Classifier: Operating System :: MacOS
Classifier: Operating System :: Microsoft :: Windows
Classifier: Operating System :: POSIX :: Linux
Classifier: Programming Language :: Python :: 3.9
Classifier: Programming Language :: Python :: 3.10
Classifier: Programming Language :: Python :: 3.11
Classifier: Programming Language :: Python :: 3.12
Classifier: Programming Language :: Python :: 3.13
Classifier: Topic :: Database
Classifier: Topic :: Scientific/Engineering :: Artificial Intelligence
Classifier: Topic :: Software Development :: Libraries :: Python Modules
Requires-Dist: pixeltable (>=0.3.8)
Project-URL: Documentation, https://docs.pixeltable.com/docs/libraries/pixelmemory
Project-URL: Homepage, https://pixeltable.com/
Project-URL: Repository, https://github.com/pixeltable/pixelmemory
